osbot_browser/Deploy.py
osbot_browser/__init__.py
osbot_browser/browser/API_Browser.py
osbot_browser/browser/API_VisJs.py
osbot_browser/browser/Browser_Commands.py
osbot_browser/browser/Browser_Lamdba_Helper.py
osbot_browser/browser/Browser_Page.py
osbot_browser/browser/Render_Page.py
osbot_browser/browser/Web_Server.py
osbot_browser/browser/__init__.py
osbot_browser/browser/sites/Site_ELK.py
osbot_browser/browser/sites/Web_Jira.py
osbot_browser/browser/sites/__init__.py
osbot_browser/lambdas/__init__.py
osbot_browser/lambdas/jira_web.py
osbot_browser/lambdas/lambda_browser.py
osbot_browser/view_helpers/Am_Charts.py
osbot_browser/view_helpers/Am_Charts_Views.py
osbot_browser/view_helpers/Base_View_Helper.py
osbot_browser/view_helpers/DataTable_Js.py
osbot_browser/view_helpers/DataTable_Js_Views.py
osbot_browser/view_helpers/Edge_Format.py
osbot_browser/view_helpers/Full_Calendar.py
osbot_browser/view_helpers/Full_Calendar_Views.py
osbot_browser/view_helpers/Go_Js.py
osbot_browser/view_helpers/Go_Js_Views.py
osbot_browser/view_helpers/Google_Charts_Js.py
osbot_browser/view_helpers/Node_Format.py
osbot_browser/view_helpers/Risk_Dashboard.py
osbot_browser/view_helpers/View_Examples.py
osbot_browser/view_helpers/Vis_Js.py
osbot_browser/view_helpers/Vis_Js_Views.py
osbot_browser/view_helpers/VivaGraph_Js.py
osbot_browser/view_helpers/VivaGraph_Js_Views.py
osbot_browser/view_helpers/__init__.py
osbot_browser-0.3.1.dist-info/LICENCE
osbot_browser-0.3.1.dist-info/METADATA
osbot_browser-0.3.1.dist-info/WHEEL
osbot_browser-0.3.1.dist-info/top_level.txt
osbot_browser-0.3.1.dist-info/RECORD
