Metadata-Version: 2.1
Name: osbot-browser
Version: 0.3.1
Summary: OWASP Security Bot - Browser APIs (serverless)
Home-page: https://github.com/pbx-gs/OSBot-GSuite
Author: Dinis Cruz
Author-email: dinis.cruz@owasp.org
License: UNKNOWN
Platform: UNKNOWN
Classifier: Programming Language :: Python :: 3
Classifier: License :: OSI Approved :: MIT License
Classifier: Operating System :: OS Independent
